setup.py
bombast/__init__.py
bombast/transform.py
bombast/utils.py
bombast.egg-info/PKG-INFO
bombast.egg-info/SOURCES.txt
bombast.egg-info/dependency_links.txt
bombast.egg-info/entry_points.txt
bombast.egg-info/requires.txt
bombast.egg-info/top_level.txt