Metadata-Version: 1.0
Name: bombast
Version: 0.2.4
Summary: An obfuscator for Python source code that manipulates the AST.
Home-page: https://github.com/brianhou/bombast
Author: Brian Hou
Author-email: UNKNOWN
License: UNKNOWN
Platform: UNKNOWN
